Workbook

Sheet Resumo
A1: Precificação por custos + margem alvo — revisão de 09/10/2026
A2: Matriz, módulo RONMA 620W, telha cerâmica, frete para Araçatuba-SP. Números recalculam a partir da aba Premissas.
A4: Números principais
A5: Reserva de elétrica calibrada (R$ por kWp) | B5: =Calibracao!B6 | C5: Antes (repasse): R$ 48,24. Subiu porque agora compara com o preço que o vendedor vê.
A6: Margem média dos promocionais (com a reserva) | B6: =Calibracao!B9 | C6: Igual à referência de 19,5% por construção.
A7: Promocionais abaixo da margem mínima | B7: =Calibracao!B11 | C7: Mínima da Matriz: 18%.
A8: Promocionais acima do preço por custos | B8: =Calibracao!B12 | C8: Só nesses o piso entra (ajuste comercial).
A9: Ajuste comercial somado nos 33 kits | B9: =Kits!AA38 | C9: Receita a mais para empatar com o promocional; não é despesa.
A10: Diferença máxima Excel × plataforma | B10: =Kits!AI38 | C10: Arredondamento de centavos (a plataforma arredonda linha a linha).
A12: Regra do preço
A13: • Custos fixos = instalação × módulos + ART + placas + projeto da Rede + reserva × kWp
A14: • Preço por custos = (kit + custos fixos − imposto × kit) ÷ (1 − comissão − imposto − margem alvo)
A15: • Piso = preço do promocional do MESMO tipo e MESMO número de placas, na unidade × (1 + adicional)
A16: • Preço final = maior entre preço por custos e piso. A diferença é o "ajuste comercial".
A17: • Sem promocional equivalente (ex.: mais de 20 placas) não há piso.
A19: O que mudou em relação ao repasse do outro chat
A20: Preço de referência | B20: Era o preço base do kit (produtos.price). Agora é o preço da Matriz, o que o vendedor vê (2% a 9% maior).
A21: Cabo 4 mm | B21: De R$ 5,87 para R$ 4,25/m (Helte, 08/10).
A22: ART | B22: Era suprimida quando a Rede cobra projeto. Agora soma sempre (decisão de 09/10).
A23: Piso promocional | B23: Era só planilha. Agora está na cotação da plataforma (modo custos), com o ajuste comercial separado.
A24: Kit 9 promocional | B24: SOFAR 4KW (sem estoque na Helte) trocado por SOFAR 5KW em 08/10.
A26: Situação na plataforma
A27: Código (commit 9bd774e no main) | B27: Pronto | C27: Falta o push.
A28: Migration do centro de custo + edge function distribuidoras | B28: Não publicado | C28: Precisam subir juntas; sem isso o modo custos não funciona.
A29: Reserva de R$ 139,83/kWp e instalação por módulo | B29: Não gravado | C29: É uma opção de teste no centro de custo; só vale depois de salvar.
A30: Markup atual | B30: Continua padrão | C30: Nada muda para o vendedor até escolherem custos.
A32: Abas
A33: Premissas | B33: Todos os valores editáveis (preços Helte, centro de custo, margem, adicional do piso).
A34: Kits | B34: Os 33 promocionais: custo, preço por custos, piso, preço final e margens.
A35: Calibracao | B35: Como a reserva por kWp é calculada e a comparação com o repasse.
A36: Cotacao | B36: Simulador para kits cotados (Belenus/Helte), com 3 cotações reais de 08/10.

Sheet Premissas
A1: Premissas do cálculo
A2: Células em azul com fundo amarelo são editáveis. O resto da planilha recalcula sozinho.
A4: Preços Helte (tabela de 06/10, cabo atualizado em 08/10)
A5: Módulo RONMA 620W (R$/un) | B5: 548 | C5: Helte, delta de preço em orçamento de teste (06/10).
A6: Potência do módulo (kW) | B6: 0.62 | C6: RONMA RM-182R/132TB 620W.
A7: Perfil 2,40 m (R$/un) | B7: 44.64 | C7: Helte (06/10).
A8: Kit fixação cerâmico 4 módulos (R$) | B8: 135.65 | C8: Helte (06/10).
A9: Kit fixação cerâmico 2 módulos (R$) | B9: 72.72 | C9: Helte (06/10).
A10: Cabo 4 mm (R$/m, por cor) | B10: 4.25 | C10: Helte baixou de 5,87 para 4,25 em 08/10 (45 cotações conferidas).
A11: Par de conectores (R$) | B11: 12 | C11: Helte (06/10).
A12: Microinversor Hoymiles 2,25 kW (R$/un) | B12: 942.49 | C12: Preço dentro do kit (06/10). 1 micro a cada 4 módulos.
A13: Fixação do micro (R$/un) | B13: 9 | C13: Helte (06/10).
A14: Frete mínimo (R$) | B14: 400 | C14: Regra levantada em 64 cotações (erro máx. R$ 0,07).
A15: Frete % (materiais abaixo do limite) | B15: 0.038494 | C15: Maior entre o mínimo e este %.
A16: Frete % (materiais a partir do limite) | B16: 0.031394
A17: Limite de materiais para o frete (R$) | B17: 25000 | C17: Comparado com as peças, sem frete.
A19: Inversores SOFAR (Helte)
A20: Potência (W) | B20: Preço (R$) | C20: Pares de conectores
A21: 3300 | B21: 1399 | C21: 1
A22: 5000 | B22: 1590 | C22: 2
A23: 6000 | B23: 1690 | C23: 2
A24: 7500 | B24: 2600 | C24: 2
A26: Centro de custo da Matriz (Financeiro → Config)
A27: Imposto (% sobre venda menos kit) | B27: 0.138 | C27: Cadastro atual da Matriz.
A28: Comissão (% sobre a venda) | B28: 0.08 | C28: Cadastro atual da Matriz (a planilha antiga da Helte usava 6%).
A29: Instalação (R$ por módulo) | B29: 70 | C29: Decisão do usuário: instaladores cobram por módulo.
A30: ART (R$ por venda) | B30: 110 | C30: Decisão de 09/10: a ART é À PARTE do projeto da Rede e soma sempre.
A31: Placas de advertência (R$ por venda) | B31: 30 | C31: Cadastro atual da Matriz.
A32: Projeto da Rede (R$ por venda) | B32: 0 | C32: A Matriz não paga projeto à Rede. Nas franquias vem da tabela por kWp (Rede → Unidades).
A33: Margem alvo | B33: 0.22 | C33: Cadastro atual da Matriz.
A34: Margem mínima | B34: 0.18 | C34: Cadastro atual da Matriz (só sinaliza).
A36: Calibração e piso
A37: Margem média de referência dos promocionais | B37: 0.195 | C37: Informada pelo usuário (hipótese comercial, não margem auditada).
A38: Reserva de elétrica (R$ por kWp) | B38: =Calibracao!$B$6 | C38: Vem da aba Calibracao. Para testar outro valor, digite um número por cima.
A39: Adicional mínimo sobre o promocional (piso) | B39: 0 | C39: Plataforma: 0% (PISO_ADICIONAL_PCT). Ex.: 5% deixa o preço final pelo menos 5% acima do promocional.
A41: Legenda:
A42: Azul com fundo amarelo | B42: valor editável
A43: Verde | B43: vem de outra aba
A44: Preto | B44: fórmula

Sheet Kits
A1: Os 33 kits promocionais: custo, preço por custos e piso
A2: Custo Helte reconstruído pela conta exata; preço promocional = o que o vendedor vê na Matriz (precos_franquia).
A3: Kit | H3: Custo Helte (conta exata) | S3: Centro de custo | Y3: Preço | AD3: Margens | AH3: Conferência
A4: Tipo | B4: Módulos | C4: kWp | D4: Inversor (W) | E4: Qtd inversores | F4: Preço base antigo (não usar) | G4: Promocional na Matriz | H4: Módulos (R$) | I4: Inversor / micros (R$) | J4: Conectores (R$) | K4: Perfis (qtd) | L4: Perfis (R$) | M4: Fixações (R$) | N4: Cabo por cor (m) | O4: Cabo (R$) | P4: Materiais (R$) | Q4: Frete (R$) | R4: Custo do kit c/ frete | S4: Instalação | T4: ART | U4: Placas | V4: Projeto Rede | W4: Reserva elétrica | X4: Custos fixos | Y4: Preço por custos (alvo) | Z4: Piso promocional | AA4: Ajuste comercial | AB4: Preço final | AC4: Final − promocional | AD4: Margem no preço final | AE4: Margem no promocional | AF4: Margem no promo. sem reserva | AG4: Abaixo da mínima? | AH4: Plataforma (JS): preço por custos | AI4: Excel − plataforma
A5: Inversor | B5: 5 | C5: =B5*Premissas!$B$6 | D5: 3300 | E5: 1 | F5: 8997 | G5: 9236.85 | H5: =B5*Premissas!$B$5 | I5: =IF(A5="Micro",E5*(Premissas!$B$12+Premissas!$B$13),E5*INDEX(Premissas!$B$21:$B$24,MATCH(D5,Premissas!$A$21:$A$24,0))) | J5: =E5*IF(A5="Micro",4,INDEX(Premissas!$C$21:$C$24,MATCH(D5,Premissas!$A$21:$A$24,0)))*Premissas!$B$11 | K5: =2*ROUNDUP(B5/2,0) | L5: =K5*Premissas!$B$7 | M5: =INT(K5/4)*Premissas!$B$8+MOD(K5,4)/2*Premissas!$B$9 | N5: =IF(B5<=19,3*B5,IF(B5<=50,ROUNDUP(2.5*B5,0),2*B5)) | O5: =2*N5*Premissas!$B$10 | P5: =H5+I5+J5+L5+M5+O5 | Q5: =IF(P5<Premissas!$B$17,MAX(Premissas!$B$14,P5*Premissas!$B$15),P5*Premissas!$B$16) | R5: =ROUND(P5+Q5,2) | S5: =B5*Premissas!$B$29 | T5: =Premissas!$B$30 | U5: =Premissas!$B$31 | V5: =Premissas!$B$32 | W5: =ROUND(Premissas!$B$38*C5,2) | X5: =S5+T5+U5+V5+W5 | Y5: =ROUNDUP((R5+X5-Premissas!$B$27*R5)/(1-Premissas!$B$28-Premissas!$B$27-Premissas!$B$33),2) | Z5: =ROUNDUP(G5*(1+Premissas!$B$39),2) | AA5: =MAX(0,Z5-Y5) | AB5: =Y5+AA5 | AC5: =AB5-G5 | AD5: =(AB5-R5-Premissas!$B$27*(AB5-R5)-Premissas!$B$28*AB5-X5)/AB5 | AE5: =(G5-R5-Premissas!$B$27*(G5-R5)-Premissas!$B$28*G5-X5)/G5 | AF5: =(G5-R5-Premissas!$B$27*(G5-R5)-Premissas!$B$28*G5-(S5+T5+U5+V5))/G5 | AG5: =IF(AE5<Premissas!$B$34,"Sim","Não") | AH5: 9549.52 | AI5: =Y5-AH5
A6: Inversor | B6: 6 | C6: =B6*Premissas!$B$6 | D6: 3300 | E6: 1 | F6: 9897 | G6: 10286.85 | H6: =B6*Premissas!$B$5 | I6: =IF(A6="Micro",E6*(Premissas!$B$12+Premissas!$B$13),E6*INDEX(Premissas!$B$21:$B$24,MATCH(D6,Premissas!$A$21:$A$24,0))) | J6: =E6*IF(A6="Micro",4,INDEX(Premissas!$C$21:$C$24,MATCH(D6,Premissas!$A$21:$A$24,0)))*Premissas!$B$11 | K6: =2*ROUNDUP(B6/2,0) | L6: =K6*Premissas!$B$7 | M6: =INT(K6/4)*Premissas!$B$8+MOD(K6,4)/2*Premissas!$B$9 | N6: =IF(B6<=19,3*B6,IF(B6<=50,ROUNDUP(2.5*B6,0),2*B6)) | O6: =2*N6*Premissas!$B$10 | P6: =H6+I6+J6+L6+M6+O6 | Q6: =IF(P6<Premissas!$B$17,MAX(Premissas!$B$14,P6*Premissas!$B$15),P6*Premissas!$B$16) | R6: =ROUND(P6+Q6,2) | S6: =B6*Premissas!$B$29 | T6: =Premissas!$B$30 | U6: =Premissas!$B$31 | V6: =Premissas!$B$32 | W6: =ROUND(Premissas!$B$38*C6,2) | X6: =S6+T6+U6+V6+W6 | Y6: =ROUNDUP((R6+X6-Premissas!$B$27*R6)/(1-Premissas!$B$28-Premissas!$B$27-Premissas!$B$33),2) | Z6: =ROUNDUP(G6*(1+Premissas!$B$39),2) | AA6: =MAX(0,Z6-Y6) | AB6: =Y6+AA6 | AC6: =AB6-G6 | AD6: =(AB6-R6-Premissas!$B$27*(AB6-R6)-Premissas!$B$28*AB6-X6)/AB6 | AE6: =(G6-R6-Premissas!$B$27*(G6-R6)-Premissas!$B$28*G6-X6)/G6 | AF6: =(G6-R6-Premissas!$B$27*(G6-R6)-Premissas!$B$28*G6-(S6+T6+U6+V6))/G6 | AG6: =IF(AE6<Premissas!$B$34,"Sim","Não") | AH6: 10707.99 | AI6: =Y6-AH6
A7: Inversor | B7: 7 | C7: =B7*Premissas!$B$6 | D7: 3300 | E7: 1 | F7: 10897 | G7: 11651.85 | H7: =B7*Premissas!$B$5 | I7: =IF(A7="Micro",E7*(Premissas!$B$12+Premissas!$B$13),E7*INDEX(Premissas!$B$21:$B$24,MATCH(D7,Premissas!$A$21:$A$24,0))) | J7: =E7*IF(A7="Micro",4,INDEX(Premissas!$C$21:$C$24,MATCH(D7,Premissas!$A$21:$A$24,0)))*Premissas!$B$11 | K7: =2*ROUNDUP(B7/2,0) | L7: =K7*Premissas!$B$7 | M7: =INT(K7/4)*Premissas!$B$8+MOD(K7,4)/2*Premissas!$B$9 | N7: =IF(B7<=19,3*B7,IF(B7<=50,ROUNDUP(2.5*B7,0),2*B7)) | O7: =2*N7*Premissas!$B$10 | P7: =H7+I7+J7+L7+M7+O7 | Q7: =IF(P7<Premissas!$B$17,MAX(Premissas!$B$14,P7*Premissas!$B$15),P7*Premissas!$B$16) | R7: =ROUND(P7+Q7,2) | S7: =B7*Premissas!$B$29 | T7: =Premissas!$B$30 | U7: =Premissas!$B$31 | V7: =Premissas!$B$32 | W7: =ROUND(Premissas!$B$38*C7,2) | X7: =S7+T7+U7+V7+W7 | Y7: =ROUNDUP((R7+X7-Premissas!$B$27*R7)/(1-Premissas!$B$28-Premissas!$B$27-Premissas!$B$33),2) | Z7: =ROUNDUP(G7*(1+Premissas!$B$39),2) | AA7: =MAX(0,Z7-Y7) | AB7: =Y7+AA7 | AC7: =AB7-G7 | AD7: =(AB7-R7-Premissas!$B$27*(AB7-R7)-Premissas!$B$28*AB7-X7)/AB7 | AE7: =(G7-R7-Premissas!$B$27*(G7-R7)-Premissas!$B$28*G7-X7)/G7 | AF7: =(G7-R7-Premissas!$B$27*(G7-R7)-Premissas!$B$28*G7-(S7+T7+U7+V7))/G7 | AG7: =IF(AE7<Premissas!$B$34,"Sim","Não") | AH7: 12099.9 | AI7: =Y7-AH7
A8: Inversor | B8: 8 | C8: =B8*Premissas!$B$6 | D8: 3300 | E8: 1 | F8: 11897 | G8: 13016.85 | H8: =B8*Premissas!$B$5 | I8: =IF(A8="Micro",E8*(Premissas!$B$12+Premissas!$B$13),E8*INDEX(Premissas!$B$21:$B$24,MATCH(D8,Premissas!$A$21:$A$24,0))) | J8: =E8*IF(A8="Micro",4,INDEX(Premissas!$C$21:$C$24,MATCH(D8,Premissas!$A$21:$A$24,0)))*Premissas!$B$11 | K8: =2*ROUNDUP(B8/2,0) | L8: =K8*Premissas!$B$7 | M8: =INT(K8/4)*Premissas!$B$8+MOD(K8,4)/2*Premissas!$B$9 | N8: =IF(B8<=19,3*B8,IF(B8<=50,ROUNDUP(2.5*B8,0),2*B8)) | O8: =2*N8*Premissas!$B$10 | P8: =H8+I8+J8+L8+M8+O8 | Q8: =IF(P8<Premissas!$B$17,MAX(Premissas!$B$14,P8*Premissas!$B$15),P8*Premissas!$B$16) | R8: =ROUND(P8+Q8,2) | S8: =B8*Premissas!$B$29 | T8: =Premissas!$B$30 | U8: =Premissas!$B$31 | V8: =Premissas!$B$32 | W8: =ROUND(Premissas!$B$38*C8,2) | X8: =S8+T8+U8+V8+W8 | Y8: =ROUNDUP((R8+X8-Premissas!$B$27*R8)/(1-Premissas!$B$28-Premissas!$B$27-Premissas!$B$33),2) | Z8: =ROUNDUP(G8*(1+Premissas!$B$39),2) | AA8: =MAX(0,Z8-Y8) | AB8: =Y8+AA8 | AC8: =AB8-G8 | AD8: =(AB8-R8-Premissas!$B$27*(AB8-R8)-Premissas!$B$28*AB8-X8)/AB8 | AE8: =(G8-R8-Premissas!$B$27*(G8-R8)-Premissas!$B$28*G8-X8)/G8 | AF8: =(G8-R8-Premissas!$B$27*(G8-R8)-Premissas!$B$28*G8-(S8+T8+U8+V8))/G8 | AG8: =IF(AE8<Premissas!$B$34,"Sim","Não") | AH8: 13258.36 | AI8: =Y8-AH8
A9: Inversor | B9: 9 | C9: =B9*Premissas!$B$6 | D9: 5000 | E9: 1 | F9: 13997 | G9: 14276.85 | H9: =B9*Premissas!$B$5 | I9: =IF(A9="Micro",E9*(Premissas!$B$12+Premissas!$B$13),E9*INDEX(Premissas!$B$21:$B$24,MATCH(D9,Premissas!$A$21:$A$24,0))) | J9: =E9*IF(A9="Micro",4,INDEX(Premissas!$C$21:$C$24,MATCH(D9,Premissas!$A$21:$A$24,0)))*Premissas!$B$11 | K9: =2*ROUNDUP(B9/2,0) | L9: =K9*Premissas!$B$7 | M9: =INT(K9/4)*Premissas!$B$8+MOD(K9,4)/2*Premissas!$B$9 | N9: =IF(B9<=19,3*B9,IF(B9<=50,ROUNDUP(2.5*B9,0),2*B9)) | O9: =2*N9*Premissas!$B$10 | P9: =H9+I9+J9+L9+M9+O9 | Q9: =IF(P9<Premissas!$B$17,MAX(Premissas!$B$14,P9*Premissas!$B$15),P9*Premissas!$B$16) | R9: =ROUND(P9+Q9,2) | S9: =B9*Premissas!$B$29 | T9: =Premissas!$B$30 | U9: =Premissas!$B$31 | V9: =Premissas!$B$32 | W9: =ROUND(Premissas!$B$38*C9,2) | X9: =S9+T9+U9+V9+W9 | Y9: =ROUNDUP((R9+X9-Premissas!$B$27*R9)/(1-Premissas!$B$28-Premissas!$B$27-Premissas!$B$33),2) | Z9: =ROUNDUP(G9*(1+Premissas!$B$39),2) | AA9: =MAX(0,Z9-Y9) | AB9: =Y9+AA9 | AC9: =AB9-G9 | AD9: =(AB9-R9-Premissas!$B$27*(AB9-R9)-Premissas!$B$28*AB9-X9)/AB9 | AE9: =(G9-R9-Premissas!$B$27*(G9-R9)-Premissas!$B$28*G9-X9)/G9 | AF9: =(G9-R9-Premissas!$B$27*(G9-R9)-Premissas!$B$28*G9-(S9+T9+U9+V9))/G9 | AG9: =IF(AE9<Premissas!$B$34,"Sim","Não") | AH9: 14976.65 | AI9: =Y9-AH9
A10: Inversor | B10: 10 | C10: =B10*Premissas!$B$6 | D10: 5000 | E10: 1 | F10: 14997 | G10: 15326.85 | H10: =B10*Premissas!$B$5 | I10: =IF(A10="Micro",E10*(Premissas!$B$12+Premissas!$B$13),E10*INDEX(Premissas!$B$21:$B$24,MATCH(D10,Premissas!$A$21:$A$24,0))) | J10: =E10*IF(A10="Micro",4,INDEX(Premissas!$C$21:$C$24,MATCH(D10,Premissas!$A$21:$A$24,0)))*Premissas!$B$11 | K10: =2*ROUNDUP(B10/2,0) | L10: =K10*Premissas!$B$7 | M10: =INT(K10/4)*Premissas!$B$8+MOD(K10,4)/2*Premissas!$B$9 | N10: =IF(B10<=19,3*B10,IF(B10<=50,ROUNDUP(2.5*B10,0),2*B10)) | O10: =2*N10*Premissas!$B$10 | P10: =H10+I10+J10+L10+M10+O10 | Q10: =IF(P10<Premissas!$B$17,MAX(Premissas!$B$14,P10*Premissas!$B$15),P10*Premissas!$B$16) | R10: =ROUND(P10+Q10,2) | S10: =B10*Premissas!$B$29 | T10: =Premissas!$B$30 | U10: =Premissas!$B$31 | V10: =Premissas!$B$32 | W10: =ROUND(Premissas!$B$38*C10,2) | X10: =S10+T10+U10+V10+W10 | Y10: =ROUNDUP((R10+X10-Premissas!$B$27*R10)/(1-Premissas!$B$28-Premissas!$B$27-Premissas!$B$33),2) | Z10: =ROUNDUP(G10*(1+Premissas!$B$39),2) | AA10: =MAX(0,Z10-Y10) | AB10: =Y10+AA10 | AC10: =AB10-G10 | AD10: =(AB10-R10-Premissas!$B$27*(AB10-R10)-Premissas!$B$28*AB10-X10)/AB10 | AE10: =(G10-R10-Premissas!$B$27*(G10-R10)-Premissas!$B$28*G10-X10)/G10 | AF10: =(G10-R10-Premissas!$B$27*(G10-R10)-Premissas!$B$28*G10-(S10+T10+U10+V10))/G10 | AG10: =IF(AE10<Premissas!$B$34,"Sim","Não") | AH10: 16135.12 | AI10: =Y10-AH10
A11: Inversor | B11: 11 | C11: =B11*Premissas!$B$6 | D11: 5000 | E11: 1 | F11: 15997 | G11: 16691.85 | H11: =B11*Premissas!$B$5 | I11: =IF(A11="Micro",E11*(Premissas!$B$12+Premissas!$B$13),E11*INDEX(Premissas!$B$21:$B$24,MATCH(D11,Premissas!$A$21:$A$24,0))) | J11: =E11*IF(A11="Micro",4,INDEX(Premissas!$C$21:$C$24,MATCH(D11,Premissas!$A$21:$A$24,0)))*Premissas!$B$11 | K11: =2*ROUNDUP(B11/2,0) | L11: =K11*Premissas!$B$7 | M11: =INT(K11/4)*Premissas!$B$8+MOD(K11,4)/2*Premissas!$B$9 | N11: =IF(B11<=19,3*B11,IF(B11<=50,ROUNDUP(2.5*B11,0),2*B11)) | O11: =2*N11*Premissas!$B$10 | P11: =H11+I11+J11+L11+M11+O11 | Q11: =IF(P11<Premissas!$B$17,MAX(Premissas!$B$14,P11*Premissas!$B$15),P11*Premissas!$B$16) | R11: =ROUND(P11+Q11,2) | S11: =B11*Premissas!$B$29 | T11: =Premissas!$B$30 | U11: =Premissas!$B$31 | V11: =Premissas!$B$32 | W11: =ROUND(Premissas!$B$38*C11,2) | X11: =S11+T11+U11+V11+W11 | Y11: =ROUNDUP((R11+X11-Premissas!$B$27*R11)/(1-Premissas!$B$28-Premissas!$B$27-Premissas!$B$33),2) | Z11: =ROUNDUP(G11*(1+Premissas!$B$39),2) | AA11: =MAX(0,Z11-Y11) | AB11: =Y11+AA11 | AC11: =AB11-G11 | AD11: =(AB11-R11-Premissas!$B$27*(AB11-R11)-Premissas!$B$28*AB11-X11)/AB11 | AE11: =(G11-R11-Premissas!$B$27*(G11-R11)-Premissas!$B$28*G11-X11)/G11 | AF11: =(G11-R11-Premissas!$B$27*(G11-R11)-Premissas!$B$28*G11-(S11+T11+U11+V11))/G11 | AG11: =IF(AE11<Premissas!$B$34,"Sim","Não") | AH11: 17527.02 | AI11: =Y11-AH11
A12: Inversor | B12: 12 | C12: =B12*Premissas!$B$6 | D12: 5000 | E12: 1 | F12: 16997 | G12: 17741.85 | H12: =B12*Premissas!$B$5 | I12: =IF(A12="Micro",E12*(Premissas!$B$12+Premissas!$B$13),E12*INDEX(Premissas!$B$21:$B$24,MATCH(D12,Premissas!$A$21:$A$24,0))) | J12: =E12*IF(A12="Micro",4,INDEX(Premissas!$C$21:$C$24,MATCH(D12,Premissas!$A$21:$A$24,0)))*Premissas!$B$11 | K12: =2*ROUNDUP(B12/2,0) | L12: =K12*Premissas!$B$7 | M12: =INT(K12/4)*Premissas!$B$8+MOD(K12,4)/2*Premissas!$B$9 | N12: =IF(B12<=19,3*B12,IF(B12<=50,ROUNDUP(2.5*B12,0),2*B12)) | O12: =2*N12*Premissas!$B$10 | P12: =H12+I12+J12+L12+M12+O12 | Q12: =IF(P12<Premissas!$B$17,MAX(Premissas!$B$14,P12*Premissas!$B$15),P12*Premissas!$B$16) | R12: =ROUND(P12+Q12,2) | S12: =B12*Premissas!$B$29 | T12: =Premissas!$B$30 | U12: =Premissas!$B$31 | V12: =Premissas!$B$32 | W12: =ROUND(Premissas!$B$38*C12,2) | X12: =S12+T12+U12+V12+W12 | Y12: =ROUNDUP((R12+X12-Premissas!$B$27*R12)/(1-Premissas!$B$28-Premissas!$B$27-Premissas!$B$33),2) | Z12: =ROUNDUP(G12*(1+Premissas!$B$39),2) | AA12: =MAX(0,Z12-Y12) | AB12: =Y12+AA12 | AC12: =AB12-G12 | AD12: =(AB12-R12-Premissas!$B$27*(AB12-R12)-Premissas!$B$28*AB12-X12)/AB12 | AE12: =(G12-R12-Premissas!$B$27*(G12-R12)-Premissas!$B$28*G12-X12)/G12 | AF12: =(G12-R12-Premissas!$B$27*(G12-R12)-Premissas!$B$28*G12-(S12+T12+U12+V12))/G12 | AG12: =IF(AE12<Premissas!$B$34,"Sim","Não") | AH12: 18685.49 | AI12: =Y12-AH12
A13: Inversor | B13: 13 | C13: =B13*Premissas!$B$6 | D13: 6000 | E13: 1 | F13: 18197 | G13: 19001.85 | H13: =B13*Premissas!$B$5 | I13: =IF(A13="Micro",E13*(Premissas!$B$12+Premissas!$B$13),E13*INDEX(Premissas!$B$21:$B$24,MATCH(D13,Premissas!$A$21:$A$24,0))) | J13: =E13*IF(A13="Micro",4,INDEX(Premissas!$C$21:$C$24,MATCH(D13,Premissas!$A$21:$A$24,0)))*Premissas!$B$11 | K13: =2*ROUNDUP(B13/2,0) | L13: =K13*Premissas!$B$7 | M13: =INT(K13/4)*Premissas!$B$8+MOD(K13,4)/2*Premissas!$B$9 | N13: =IF(B13<=19,3*B13,IF(B13<=50,ROUNDUP(2.5*B13,0),2*B13)) | O13: =2*N13*Premissas!$B$10 | P13: =H13+I13+J13+L13+M13+O13 | Q13: =IF(P13<Premissas!$B$17,MAX(Premissas!$B$14,P13*Premissas!$B$15),P13*Premissas!$B$16) | R13: =ROUND(P13+Q13,2) | S13: =B13*Premissas!$B$29 | T13: =Premissas!$B$30 | U13: =Premissas!$B$31 | V13: =Premissas!$B$32 | W13: =ROUND(Premissas!$B$38*C13,2) | X13: =S13+T13+U13+V13+W13 | Y13: =ROUNDUP((R13+X13-Premissas!$B$27*R13)/(1-Premissas!$B$28-Premissas!$B$27-Premissas!$B$33),2) | Z13: =ROUNDUP(G13*(1+Premissas!$B$39),2) | AA13: =MAX(0,Z13-Y13) | AB13: =Y13+AA13 | AC13: =AB13-G13 | AD13: =(AB13-R13-Premissas!$B$27*(AB13-R13)-Premissas!$B$28*AB13-X13)/AB13 | AE13: =(G13-R13-Premissas!$B$27*(G13-R13)-Premissas!$B$28*G13-X13)/G13 | AF13: =(G13-R13-Premissas!$B$27*(G13-R13)-Premissas!$B$28*G13-(S13+T13+U13+V13))/G13 | AG13: =IF(AE13<Premissas!$B$34,"Sim","Não") | AH13: 20245.79 | AI13: =Y13-AH13
A14: Inversor | B14: 14 | C14: =B14*Premissas!$B$6 | D14: 6000 | E14: 1 | F14: 19897 | G14: 20261.85 | H14: =B14*Premissas!$B$5 | I14: =IF(A14="Micro",E14*(Premissas!$B$12+Premissas!$B$13),E14*INDEX(Premissas!$B$21:$B$24,MATCH(D14,Premissas!$A$21:$A$24,0))) | J14: =E14*IF(A14="Micro",4,INDEX(Premissas!$C$21:$C$24,MATCH(D14,Premissas!$A$21:$A$24,0)))*Premissas!$B$11 | K14: =2*ROUNDUP(B14/2,0) | L14: =K14*Premissas!$B$7 | M14: =INT(K14/4)*Premissas!$B$8+MOD(K14,4)/2*Premissas!$B$9 | N14: =IF(B14<=19,3*B14,IF(B14<=50,ROUNDUP(2.5*B14,0),2*B14)) | O14: =2*N14*Premissas!$B$10 | P14: =H14+I14+J14+L14+M14+O14 | Q14: =IF(P14<Premissas!$B$17,MAX(Premissas!$B$14,P14*Premissas!$B$15),P14*Premissas!$B$16) | R14: =ROUND(P14+Q14,2) | S14: =B14*Premissas!$B$29 | T14: =Premissas!$B$30 | U14: =Premissas!$B$31 | V14: =Premissas!$B$32 | W14: =ROUND(Premissas!$B$38*C14,2) | X14: =S14+T14+U14+V14+W14 | Y14: =ROUNDUP((R14+X14-Premissas!$B$27*R14)/(1-Premissas!$B$28-Premissas!$B$27-Premissas!$B$33),2) | Z14: =ROUNDUP(G14*(1+Premissas!$B$39),2) | AA14: =MAX(0,Z14-Y14) | AB14: =Y14+AA14 | AC14: =AB14-G14 | AD14: =(AB14-R14-Premissas!$B$27*(AB14-R14)-Premissas!$B$28*AB14-X14)/AB14 | AE14: =(G14-R14-Premissas!$B$27*(G14-R14)-Premissas!$B$28*G14-X14)/G14 | AF14: =(G14-R14-Premissas!$B$27*(G14-R14)-Premissas!$B$28*G14-(S14+T14+U14+V14))/G14 | AG14: =IF(AE14<Premissas!$B$34,"Sim","Não") | AH14: 21431.18 | AI14: =Y14-AH14
A15: Inversor | B15: 15 | C15: =B15*Premissas!$B$6 | D15: 6000 | E15: 1 | F15: 20597 | G15: 21626.85 | H15: =B15*Premissas!$B$5 | I15: =IF(A15="Micro",E15*(Premissas!$B$12+Premissas!$B$13),E15*INDEX(Premissas!$B$21:$B$24,MATCH(D15,Premissas!$A$21:$A$24,0))) | J15: =E15*IF(A15="Micro",4,INDEX(Premissas!$C$21:$C$24,MATCH(D15,Premissas!$A$21:$A$24,0)))*Premissas!$B$11 | K15: =2*ROUNDUP(B15/2,0) | L15: =K15*Premissas!$B$7 | M15: =INT(K15/4)*Premissas!$B$8+MOD(K15,4)/2*Premissas!$B$9 | N15: =IF(B15<=19,3*B15,IF(B15<=50,ROUNDUP(2.5*B15,0),2*B15)) | O15: =2*N15*Premissas!$B$10 | P15: =H15+I15+J15+L15+M15+O15 | Q15: =IF(P15<Premissas!$B$17,MAX(Premissas!$B$14,P15*Premissas!$B$15),P15*Premissas!$B$16) | R15: =ROUND(P15+Q15,2) | S15: =B15*Premissas!$B$29 | T15: =Premissas!$B$30 | U15: =Premissas!$B$31 | V15: =Premissas!$B$32 | W15: =ROUND(Premissas!$B$38*C15,2) | X15: =S15+T15+U15+V15+W15 | Y15: =ROUNDUP((R15+X15-Premissas!$B$27*R15)/(1-Premissas!$B$28-Premissas!$B$27-Premissas!$B$33),2) | Z15: =ROUNDUP(G15*(1+Premissas!$B$39),2) | AA15: =MAX(0,Z15-Y15) | AB15: =Y15+AA15 | AC15: =AB15-G15 | AD15: =(AB15-R15-Premissas!$B$27*(AB15-R15)-Premissas!$B$28*AB15-X15)/AB15 | AE15: =(G15-R15-Premissas!$B$27*(G15-R15)-Premissas!$B$28*G15-X15)/G15 | AF15: =(G15-R15-Premissas!$B$27*(G15-R15)-Premissas!$B$28*G15-(S15+T15+U15+V15))/G15 | AG15: =IF(AE15<Premissas!$B$34,"Sim","Não") | AH15: 22865.95 | AI15: =Y15-AH15
A16: Inversor | B16: 16 | C16: =B16*Premissas!$B$6 | D16: 6000 | E16: 1 | F16: 21697 | G16: 22676.85 | H16: =B16*Premissas!$B$5 | I16: =IF(A16="Micro",E16*(Premissas!$B$12+Premissas!$B$13),E16*INDEX(Premissas!$B$21:$B$24,MATCH(D16,Premissas!$A$21:$A$24,0))) | J16: =E16*IF(A16="Micro",4,INDEX(Premissas!$C$21:$C$24,MATCH(D16,Premissas!$A$21:$A$24,0)))*Premissas!$B$11 | K16: =2*ROUNDUP(B16/2,0) | L16: =K16*Premissas!$B$7 | M16: =INT(K16/4)*Premissas!$B$8+MOD(K16,4)/2*Premissas!$B$9 | N16: =IF(B16<=19,3*B16,IF(B16<=50,ROUNDUP(2.5*B16,0),2*B16)) | O16: =2*N16*Premissas!$B$10 | P16: =H16+I16+J16+L16+M16+O16 | Q16: =IF(P16<Premissas!$B$17,MAX(Premissas!$B$14,P16*Premissas!$B$15),P16*Premissas!$B$16) | R16: =ROUND(P16+Q16,2) | S16: =B16*Premissas!$B$29 | T16: =Premissas!$B$30 | U16: =Premissas!$B$31 | V16: =Premissas!$B$32 | W16: =ROUND(Premissas!$B$38*C16,2) | X16: =S16+T16+U16+V16+W16 | Y16: =ROUNDUP((R16+X16-Premissas!$B$27*R16)/(1-Premissas!$B$28-Premissas!$B$27-Premissas!$B$33),2) | Z16: =ROUNDUP(G16*(1+Premissas!$B$39),2) | AA16: =MAX(0,Z16-Y16) | AB16: =Y16+AA16 | AC16: =AB16-G16 | AD16: =(AB16-R16-Premissas!$B$27*(AB16-R16)-Premissas!$B$28*AB16-X16)/AB16 | AE16: =(G16-R16-Premissas!$B$27*(G16-R16)-Premissas!$B$28*G16-X16)/G16 | AF16: =(G16-R16-Premissas!$B$27*(G16-R16)-Premissas!$B$28*G16-(S16+T16+U16+V16))/G16 | AG16: =IF(AE16<Premissas!$B$34,"Sim","Não") | AH16: 24058.26 | AI16: =Y16-AH16
... A37: Micro | B37: 20 | C37: =B37*Premissas!$B$6 | D37: 2250 | E37: 5 | F37: 30397 | G37: 32555.19 | H37: =B37*Premissas!$B$5 | I37: =IF(A37="Micro",E37*(Premissas!$B$12+Premissas!$B$13),E37*INDEX(Premissas!$B$21:$B$24,MATCH(D37,Premissas!$A$21:$A$24,0))) | J37: =E37*IF(A37="Micro",4,INDEX(Premissas!$C$21:$C$24,MATCH(D37,Premissas!$A$21:$A$24,0)))*Premissas!$B$11 | K37: =2*ROUNDUP(B37/2,0) | L37: =K37*Premissas!$B$7 | M37: =INT(K37/4)*Premissas!$B$8+MOD(K37,4)/2*Premissas!$B$9 | N37: =IF(B37<=19,3*B37,IF(B37<=50,ROUNDUP(2.5*B37,0),2*B37)) | O37: =2*N37*Premissas!$B$10 | P37: =H37+I37+J37+L37+M37+O37 | Q37: =IF(P37<Premissas!$B$17,MAX(Premissas!$B$14,P37*Premissas!$B$15),P37*Premissas!$B$16) | R37: =ROUND(P37+Q37,2) | S37: =B37*Premissas!$B$29 | T37: =Premissas!$B$30 | U37: =Premissas!$B$31 | V37: =Premissas!$B$32 | W37: =ROUND(Premissas!$B$38*C37,2) | X37: =S37+T37+U37+V37+W37 | Y37: =ROUNDUP((R37+X37-Premissas!$B$27*R37)/(1-Premissas!$B$28-Premissas!$B$27-Premissas!$B$33),2) | Z37: =ROUNDUP(G37*(1+Premissas!$B$39),2) | AA37: =MAX(0,Z37-Y37) | AB37: =Y37+AA37 | AC37: =AB37-G37 | AD37: =(AB37-R37-Premissas!$B$27*(AB37-R37)-Premissas!$B$28*AB37-X37)/AB37 | AE37: =(G37-R37-Premissas!$B$27*(G37-R37)-Premissas!$B$28*G37-X37)/G37 | AF37: =(G37-R37-Premissas!$B$27*(G37-R37)-Premissas!$B$28*G37-(S37+T37+U37+V37))/G37 | AG37: =IF(AE37<Premissas!$B$34,"Sim","Não") | AH37: 34422.67 | AI37: =Y37-AH37
A38: Média | AA38: =SUM(AA5:AA37) | AD38: =AVERAGE(AD5:AD37) | AE38: =AVERAGE(AE5:AE37) | AF38: =AVERAGE(AF5:AF37) | AI38: =MAX(AI5:AI37)-MIN(AI5:AI37)

Sheet Calibracao
A1: Calibração da reserva de elétrica (engenharia reversa)
A2: Qual reserva por kWp faz a margem média dos 33 promocionais (preço da Matriz) dar a margem de referência?
A4: Soma de (margem sem reserva − margem de referência) | B4: =SUM(Kits!$AF$5:$AF$37)-COUNT(Kits!$AF$5:$AF$37)*Premissas!$B$37
A5: Soma de (kWp ÷ preço promocional) | B5: =SUMPRODUCT(Kits!$C$5:$C$37/Kits!$G$5:$G$37)
A6: Reserva calibrada (R$ por kWp) | B6: =ROUND(MAX(0,B4/B5),2) | C6: Usada em Premissas. Fórmula: média de [(lucro sem reserva − reserva × kWp) ÷ preço] = margem de referência.
A8: Conferência com a reserva em uso
A9: Margem média no promocional (peso igual por kit) | B9: =AVERAGE(Kits!$AE$5:$AE$37)
A10: Margem média ponderada pelo preço | B10: =SUMPRODUCT(Kits!$AE$5:$AE$37,Kits!$G$5:$G$37)/SUM(Kits!$G$5:$G$37)
A11: Kits com margem abaixo da mínima no promocional | B11: =COUNTIF(Kits!$AG$5:$AG$37,"Sim")
A12: Kits em que o promocional fica acima do preço por custos | B12: =SUMPRODUCT(--(Kits!$G$5:$G$37>Kits!$Y$5:$Y$37)) | C12: Nesses o piso promocional sobe o preço (ajuste comercial).
A13: Sensibilidade: reserva sem os micros de 4 a 7 módulos | B13: =ROUND((SUMPRODUCT(--(((Kits!$A$5:$A$37="Inversor")+(Kits!$B$5:$B$37>7))>0),Kits!$AF$5:$AF$37)-SUMPRODUCT(--(((Kits!$A$5:$A$37="Inversor")+(Kits!$B$5:$B$37>7))>0))*Premissas!$B$37)/SUMPRODUCT(--(((Kits!$A$5:$A$37="Inversor")+(Kits!$B$5:$B$37>7))>0),Kits!$C$5:$C$37/Kits!$G$5:$G$37),2) | C13: Os micros pequenos puxam a reserva; mostra quanto a estimativa é sensível.
A15: Antes × agora
A16: Cenário | B16: Reserva (R$/kWp) | C16: O que mudou
A17: Repasse do outro chat (preço base, cabo 5,87) | B17: 48.24 | C17: Valor histórico do repasse (scripts/calibrar-centro-custo.cjs, versão de 09/10 de manhã).
A18: Agora (preço da Matriz, cabo 4,25) | B18: =B6 | C18: Preço que o vendedor vê (+0% a 9,4%) e cabo novo da Helte.
A20: A reserva é um ajuste para fechar a conta, não um custo medido de elétrica. Quando os custos reais forem lançados, tirar a parte correspondente daqui.

Sheet Cotacao
A1: Simulador: kit cotado na distribuidora + piso promocional
A2: Preencha as colunas em amarelo. O piso usa o promocional do mesmo tipo com o mesmo número de placas (regra da plataforma).
A4: Distribuidora | B4: Descrição | C4: Tipo (Inversor/Micro) | D4: Placas | E4: kWp | F4: Custo do kit c/ frete | G4: Custos fixos | H4: Preço por custos | I4: Promocional equivalente | J4: Piso | K4: Ajuste comercial | L4: Preço final | M4: Margem no preço final | N4: Observação
A5: Belenus | B5: KIT 6 MOD. 580W + INV. GROWATT 3KW (cotação real 08/10) | C5: Inversor | D5: 6 | E5: 3.48 | F5: 6025.04 | G5: =IF(OR(D5="",E5="",F5=""),"",D5*Premissas!$B$29+Premissas!$B$30+Premissas!$B$31+Premissas!$B$32+ROUND(Premissas!$B$38*E5,2)) | H5: =IF(OR(D5="",E5="",F5=""),"",ROUNDUP((F5+G5-Premissas!$B$27*F5)/(1-Premissas!$B$28-Premissas!$B$27-Premissas!$B$33),2)) | I5: =IF(OR(D5="",E5="",F5=""),"",IF(COUNTIFS(Kits!$A$5:$A$37,C5,Kits!$B$5:$B$37,D5)=0,"",SUMIFS(Kits!$G$5:$G$37,Kits!$A$5:$A$37,C5,Kits!$B$5:$B$37,D5))) | J5: =IF(I5="","",ROUNDUP(I5*(1+Premissas!$B$39),2)) | K5: =IF(H5="","",IF(J5="",0,MAX(0,J5-H5))) | L5: =IF(H5="","",H5+K5) | M5: =IF(L5="","",(L5-F5-Premissas!$B$27*(L5-F5)-Premissas!$B$28*L5-G5)/L5) | N5: =IF(H5="","",IF(I5="","Sem promocional "&LOWER(C5)&" com "&D5&" placas: sem piso",IF(K5>0,"Subiu para o promocional","Acima do promocional")))
A6: Belenus | B6: KIT 6 MOD. 580W + INV. SOLIS 3KW (cotação real 08/10) | C6: Inversor | D6: 6 | E6: 3.48 | F6: 6817.13 | G6: =IF(OR(D6="",E6="",F6=""),"",D6*Premissas!$B$29+Premissas!$B$30+Premissas!$B$31+Premissas!$B$32+ROUND(Premissas!$B$38*E6,2)) | H6: =IF(OR(D6="",E6="",F6=""),"",ROUNDUP((F6+G6-Premissas!$B$27*F6)/(1-Premissas!$B$28-Premissas!$B$27-Premissas!$B$33),2)) | I6: =IF(OR(D6="",E6="",F6=""),"",IF(COUNTIFS(Kits!$A$5:$A$37,C6,Kits!$B$5:$B$37,D6)=0,"",SUMIFS(Kits!$G$5:$G$37,Kits!$A$5:$A$37,C6,Kits!$B$5:$B$37,D6))) | J6: =IF(I6="","",ROUNDUP(I6*(1+Premissas!$B$39),2)) | K6: =IF(H6="","",IF(J6="",0,MAX(0,J6-H6))) | L6: =IF(H6="","",H6+K6) | M6: =IF(L6="","",(L6-F6-Premissas!$B$27*(L6-F6)-Premissas!$B$28*L6-G6)/L6) | N6: =IF(H6="","",IF(I6="","Sem promocional "&LOWER(C6)&" com "&D6&" placas: sem piso",IF(K6>0,"Subiu para o promocional","Acima do promocional")))
A7: Helte | B7: KIT 9 MOD. 620W + INV. SOFAR 5KW (cotação real 08/10) | C7: Inversor | D7: 9 | E7: 5.58 | F7: 7965.87 | G7: =IF(OR(D7="",E7="",F7=""),"",D7*Premissas!$B$29+Premissas!$B$30+Premissas!$B$31+Premissas!$B$32+ROUND(Premissas!$B$38*E7,2)) | H7: =IF(OR(D7="",E7="",F7=""),"",ROUNDUP((F7+G7-Premissas!$B$27*F7)/(1-Premissas!$B$28-Premissas!$B$27-Premissas!$B$33),2)) | I7: =IF(OR(D7="",E7="",F7=""),"",IF(COUNTIFS(Kits!$A$5:$A$37,C7,Kits!$B$5:$B$37,D7)=0,"",SUMIFS(Kits!$G$5:$G$37,Kits!$A$5:$A$37,C7,Kits!$B$5:$B$37,D7))) | J7: =IF(I7="","",ROUNDUP(I7*(1+Premissas!$B$39),2)) | K7: =IF(H7="","",IF(J7="",0,MAX(0,J7-H7))) | L7: =IF(H7="","",H7+K7) | M7: =IF(L7="","",(L7-F7-Premissas!$B$27*(L7-F7)-Premissas!$B$28*L7-G7)/L7) | N7: =IF(H7="","",IF(I7="","Sem promocional "&LOWER(C7)&" com "&D7&" placas: sem piso",IF(K7>0,"Subiu para o promocional","Acima do promocional")))
G8: =IF(OR(D8="",E8="",F8=""),"",D8*Premissas!$B$29+Premissas!$B$30+Premissas!$B$31+Premissas!$B$32+ROUND(Premissas!$B$38*E8,2)) | H8: =IF(OR(D8="",E8="",F8=""),"",ROUNDUP((F8+G8-Premissas!$B$27*F8)/(1-Premissas!$B$28-Premissas!$B$27-Premissas!$B$33),2)) | I8: =IF(OR(D8="",E8="",F8=""),"",IF(COUNTIFS(Kits!$A$5:$A$37,C8,Kits!$B$5:$B$37,D8)=0,"",SUMIFS(Kits!$G$5:$G$37,Kits!$A$5:$A$37,C8,Kits!$B$5:$B$37,D8))) | J8: =IF(I8="","",ROUNDUP(I8*(1+Premissas!$B$39),2)) | K8: =IF(H8="","",IF(J8="",0,MAX(0,J8-H8))) | L8: =IF(H8="","",H8+K8) | M8: =IF(L8="","",(L8-F8-Premissas!$B$27*(L8-F8)-Premissas!$B$28*L8-G8)/L8) | N8: =IF(H8="","",IF(I8="","Sem promocional "&LOWER(C8)&" com "&D8&" placas: sem piso",IF(K8>0,"Subiu para o promocional","Acima do promocional")))
G9: =IF(OR(D9="",E9="",F9=""),"",D9*Premissas!$B$29+Premissas!$B$30+Premissas!$B$31+Premissas!$B$32+ROUND(Premissas!$B$38*E9,2)) | H9: =IF(OR(D9="",E9="",F9=""),"",ROUNDUP((F9+G9-Premissas!$B$27*F9)/(1-Premissas!$B$28-Premissas!$B$27-Premissas!$B$33),2)) | I9: =IF(OR(D9="",E9="",F9=""),"",IF(COUNTIFS(Kits!$A$5:$A$37,C9,Kits!$B$5:$B$37,D9)=0,"",SUMIFS(Kits!$G$5:$G$37,Kits!$A$5:$A$37,C9,Kits!$B$5:$B$37,D9))) | J9: =IF(I9="","",ROUNDUP(I9*(1+Premissas!$B$39),2)) | K9: =IF(H9="","",IF(J9="",0,MAX(0,J9-H9))) | L9: =IF(H9="","",H9+K9) | M9: =IF(L9="","",(L9-F9-Premissas!$B$27*(L9-F9)-Premissas!$B$28*L9-G9)/L9) | N9: =IF(H9="","",IF(I9="","Sem promocional "&LOWER(C9)&" com "&D9&" placas: sem piso",IF(K9>0,"Subiu para o promocional","Acima do promocional")))
G10: =IF(OR(D10="",E10="",F10=""),"",D10*Premissas!$B$29+Premissas!$B$30+Premissas!$B$31+Premissas!$B$32+ROUND(Premissas!$B$38*E10,2)) | H10: =IF(OR(D10="",E10="",F10=""),"",ROUNDUP((F10+G10-Premissas!$B$27*F10)/(1-Premissas!$B$28-Premissas!$B$27-Premissas!$B$33),2)) | I10: =IF(OR(D10="",E10="",F10=""),"",IF(COUNTIFS(Kits!$A$5:$A$37,C10,Kits!$B$5:$B$37,D10)=0,"",SUMIFS(Kits!$G$5:$G$37,Kits!$A$5:$A$37,C10,Kits!$B$5:$B$37,D10))) | J10: =IF(I10="","",ROUNDUP(I10*(1+Premissas!$B$39),2)) | K10: =IF(H10="","",IF(J10="",0,MAX(0,J10-H10))) | L10: =IF(H10="","",H10+K10) | M10: =IF(L10="","",(L10-F10-Premissas!$B$27*(L10-F10)-Premissas!$B$28*L10-G10)/L10) | N10: =IF(H10="","",IF(I10="","Sem promocional "&LOWER(C10)&" com "&D10&" placas: sem piso",IF(K10>0,"Subiu para o promocional","Acima do promocional")))
G11: =IF(OR(D11="",E11="",F11=""),"",D11*Premissas!$B$29+Premissas!$B$30+Premissas!$B$31+Premissas!$B$32+ROUND(Premissas!$B$38*E11,2)) | H11: =IF(OR(D11="",E11="",F11=""),"",ROUNDUP((F11+G11-Premissas!$B$27*F11)/(1-Premissas!$B$28-Premissas!$B$27-Premissas!$B$33),2)) | I11: =IF(OR(D11="",E11="",F11=""),"",IF(COUNTIFS(Kits!$A$5:$A$37,C11,Kits!$B$5:$B$37,D11)=0,"",SUMIFS(Kits!$G$5:$G$37,Kits!$A$5:$A$37,C11,Kits!$B$5:$B$37,D11))) | J11: =IF(I11="","",ROUNDUP(I11*(1+Premissas!$B$39),2)) | K11: =IF(H11="","",IF(J11="",0,MAX(0,J11-H11))) | L11: =IF(H11="","",H11+K11) | M11: =IF(L11="","",(L11-F11-Premissas!$B$27*(L11-F11)-Premissas!$B$28*L11-G11)/L11) | N11: =IF(H11="","",IF(I11="","Sem promocional "&LOWER(C11)&" com "&D11&" placas: sem piso",IF(K11>0,"Subiu para o promocional","Acima do promocional")))
G12: =IF(OR(D12="",E12="",F12=""),"",D12*Premissas!$B$29+Premissas!$B$30+Premissas!$B$31+Premissas!$B$32+ROUND(Premissas!$B$38*E12,2)) | H12: =IF(OR(D12="",E12="",F12=""),"",ROUNDUP((F12+G12-Premissas!$B$27*F12)/(1-Premissas!$B$28-Premissas!$B$27-Premissas!$B$33),2)) | I12: =IF(OR(D12="",E12="",F12=""),"",IF(COUNTIFS(Kits!$A$5:$A$37,C12,Kits!$B$5:$B$37,D12)=0,"",SUMIFS(Kits!$G$5:$G$37,Kits!$A$5:$A$37,C12,Kits!$B$5:$B$37,D12))) | J12: =IF(I12="","",ROUNDUP(I12*(1+Premissas!$B$39),2)) | K12: =IF(H12="","",IF(J12="",0,MAX(0,J12-H12))) | L12: =IF(H12="","",H12+K12) | M12: =IF(L12="","",(L12-F12-Premissas!$B$27*(L12-F12)-Premissas!$B$28*L12-G12)/L12) | N12: =IF(H12="","",IF(I12="","Sem promocional "&LOWER(C12)&" com "&D12&" placas: sem piso",IF(K12>0,"Subiu para o promocional","Acima do promocional")))
G13: =IF(OR(D13="",E13="",F13=""),"",D13*Premissas!$B$29+Premissas!$B$30+Premissas!$B$31+Premissas!$B$32+ROUND(Premissas!$B$38*E13,2)) | H13: =IF(OR(D13="",E13="",F13=""),"",ROUNDUP((F13+G13-Premissas!$B$27*F13)/(1-Premissas!$B$28-Premissas!$B$27-Premissas!$B$33),2)) | I13: =IF(OR(D13="",E13="",F13=""),"",IF(COUNTIFS(Kits!$A$5:$A$37,C13,Kits!$B$5:$B$37,D13)=0,"",SUMIFS(Kits!$G$5:$G$37,Kits!$A$5:$A$37,C13,Kits!$B$5:$B$37,D13))) | J13: =IF(I13="","",ROUNDUP(I13*(1+Premissas!$B$39),2)) | K13: =IF(H13="","",IF(J13="",0,MAX(0,J13-H13))) | L13: =IF(H13="","",H13+K13) | M13: =IF(L13="","",(L13-F13-Premissas!$B$27*(L13-F13)-Premissas!$B$28*L13-G13)/L13) | N13: =IF(H13="","",IF(I13="","Sem promocional "&LOWER(C13)&" com "&D13&" placas: sem piso",IF(K13>0,"Subiu para o promocional","Acima do promocional")))
G14: =IF(OR(D14="",E14="",F14=""),"",D14*Premissas!$B$29+Premissas!$B$30+Premissas!$B$31+Premissas!$B$32+ROUND(Premissas!$B$38*E14,2)) | H14: =IF(OR(D14="",E14="",F14=""),"",ROUNDUP((F14+G14-Premissas!$B$27*F14)/(1-Premissas!$B$28-Premissas!$B$27-Premissas!$B$33),2)) | I14: =IF(OR(D14="",E14="",F14=""),"",IF(COUNTIFS(Kits!$A$5:$A$37,C14,Kits!$B$5:$B$37,D14)=0,"",SUMIFS(Kits!$G$5:$G$37,Kits!$A$5:$A$37,C14,Kits!$B$5:$B$37,D14))) | J14: =IF(I14="","",ROUNDUP(I14*(1+Premissas!$B$39),2)) | K14: =IF(H14="","",IF(J14="",0,MAX(0,J14-H14))) | L14: =IF(H14="","",H14+K14) | M14: =IF(L14="","",(L14-F14-Premissas!$B$27*(L14-F14)-Premissas!$B$28*L14-G14)/L14) | N14: =IF(H14="","",IF(I14="","Sem promocional "&LOWER(C14)&" com "&D14&" placas: sem piso",IF(K14>0,"Subiu para o promocional","Acima do promocional")))
G15: =IF(OR(D15="",E15="",F15=""),"",D15*Premissas!$B$29+Premissas!$B$30+Premissas!$B$31+Premissas!$B$32+ROUND(Premissas!$B$38*E15,2)) | H15: =IF(OR(D15="",E15="",F15=""),"",ROUNDUP((F15+G15-Premissas!$B$27*F15)/(1-Premissas!$B$28-Premissas!$B$27-Premissas!$B$33),2)) | I15: =IF(OR(D15="",E15="",F15=""),"",IF(COUNTIFS(Kits!$A$5:$A$37,C15,Kits!$B$5:$B$37,D15)=0,"",SUMIFS(Kits!$G$5:$G$37,Kits!$A$5:$A$37,C15,Kits!$B$5:$B$37,D15))) | J15: =IF(I15="","",ROUNDUP(I15*(1+Premissas!$B$39),2)) | K15: =IF(H15="","",IF(J15="",0,MAX(0,J15-H15))) | L15: =IF(H15="","",H15+K15) | M15: =IF(L15="","",(L15-F15-Premissas!$B$27*(L15-F15)-Premissas!$B$28*L15-G15)/L15) | N15: =IF(H15="","",IF(I15="","Sem promocional "&LOWER(C15)&" com "&D15&" placas: sem piso",IF(K15>0,"Subiu para o promocional","Acima do promocional")))
G16: =IF(OR(D16="",E16="",F16=""),"",D16*Premissas!$B$29+Premissas!$B$30+Premissas!$B$31+Premissas!$B$32+ROUND(Premissas!$B$38*E16,2)) | H16: =IF(OR(D16="",E16="",F16=""),"",ROUNDUP((F16+G16-Premissas!$B$27*F16)/(1-Premissas!$B$28-Premissas!$B$27-Premissas!$B$33),2)) | I16: =IF(OR(D16="",E16="",F16=""),"",IF(COUNTIFS(Kits!$A$5:$A$37,C16,Kits!$B$5:$B$37,D16)=0,"",SUMIFS(Kits!$G$5:$G$37,Kits!$A$5:$A$37,C16,Kits!$B$5:$B$37,D16))) | J16: =IF(I16="","",ROUNDUP(I16*(1+Premissas!$B$39),2)) | K16: =IF(H16="","",IF(J16="",0,MAX(0,J16-H16))) | L16: =IF(H16="","",H16+K16) | M16: =IF(L16="","",(L16-F16-Premissas!$B$27*(L16-F16)-Premissas!$B$28*L16-G16)/L16) | N16: =IF(H16="","",IF(I16="","Sem promocional "&LOWER(C16)&" com "&D16&" placas: sem piso",IF(K16>0,"Subiu para o promocional","Acima do promocional")))
